bubot/__init__.py
bubot/__main__.py
bubot/Ocf/CloudCoapTcpClient.py
bubot/Ocf/ConnectivityAbstractionLayer.py
bubot/Ocf/DeviceClient.py
bubot/Ocf/DeviceServer.py
bubot/Ocf/Ep.py
bubot/Ocf/Helper.py
bubot/Ocf/OcfMessage.py
bubot/Ocf/PersistentStorage.py
bubot/Ocf/PolicyEngine.py
bubot/Ocf/ResourceLayer.py
bubot/Ocf/Session.py
bubot/Ocf/TransporLayer.py
bubot/Ocf/__init__.py
bubot/Ocf/const.py
bubot/OcfResource/OcfResource.py
bubot/OcfResource/OicRAcl2.py
bubot/OcfResource/OicRCoapCloudConf.py
bubot/OcfResource/OicRCred.py
bubot/OcfResource/OicRDoxm.py
bubot/OcfResource/OicRPstat.py
bubot/OcfResource/OicRSdi.py
bubot/OcfResource/OicSecSession.py
bubot/OcfResource/OicWkRes.py
bubot/buject/__init__.py
bubot/buject/ObjAction/ObjAction.py
bubot/buject/ObjAction/__init__.py
bubot/buject/ObjSchema/ObjSchema.py
bubot/buject/ObjSchema/ObjSchemaApi.py
bubot/buject/ObjSchema/__init__.py
bubot/buject/OcfDevice/subtype/Console/Console.json
bubot/buject/OcfDevice/subtype/Console/Console.py
bubot/buject/OcfDevice/subtype/Console/__init__.py
bubot/buject/OcfDevice/subtype/Device/Device.json
bubot/buject/OcfDevice/subtype/Device/Device.md
bubot/buject/OcfDevice/subtype/Device/Device.py
bubot/buject/OcfDevice/subtype/Device/DeviceCore.py
bubot/buject/OcfDevice/subtype/Device/MainLoopMixin.py
bubot/buject/OcfDevice/subtype/Device/QueueMixin.py
bubot/buject/OcfDevice/subtype/Device/RedisQueueMixin.py
bubot/buject/OcfDevice/subtype/Device/__init__.py
bubot/buject/OcfDevice/subtype/EchoDevice/EchoDevice.json
bubot/buject/OcfDevice/subtype/EchoDevice/EchoDevice.py
bubot/buject/OcfDevice/subtype/EchoDevice/__init__.py
bubot/buject/OcfDevice/subtype/VirtualServer/VirtualServer.json
bubot/buject/OcfDevice/subtype/VirtualServer/VirtualServer.md
bubot/buject/OcfDevice/subtype/VirtualServer/VirtualServer.py
bubot/buject/OcfDevice/subtype/VirtualServer/__init__.py
bubot/buject/OcfSchema/schema/BuDeviceConfiguration.json
bubot/buject/OcfSchema/schema/BuSerialPortConfiguration.json
bubot_core-4.1.3.dist-info/licenses/LICENSE
bubot_core-4.1.3.dist-info/METADATA
bubot_core-4.1.3.dist-info/WHEEL
bubot_core-4.1.3.dist-info/entry_points.txt
bubot_core-4.1.3.dist-info/top_level.txt
bubot_core-4.1.3.dist-info/RECORD
