Metadata-Version: 2.4
Name: bubot_core
Version: 4.1.3
Summary: iot framework based on OCF specification
Home-page: https://github.com/businka/Bubot_Core
Author: Razgovorov Mikhail
Author-email: 1338833@gmail.com
Classifier: Programming Language :: Python :: 3
Classifier: License :: OSI Approved :: MIT License
Classifier: Operating System :: OS Independent
Classifier: Framework :: AsyncIO
Requires-Python: >=3.8
License-File: LICENSE
Requires-Dist: cbor2>5
Requires-Dist: Bubot_Helpers>=4.0.3
Requires-Dist: Bubot_CoAP>=2.0.0
Dynamic: author
Dynamic: author-email
Dynamic: classifier
Dynamic: description
Dynamic: description-content-type
Dynamic: home-page
Dynamic: license-file
Dynamic: requires-dist
Dynamic: requires-python
Dynamic: summary
